README
setup.cfg
setup.py
splparser/__init__.py
splparser/decorators.py
splparser/exceptions.py
splparser/parser.py
splparser/parsetree.py
splparser/schema.py
splparser.egg-info/PKG-INFO
splparser.egg-info/SOURCES.txt
splparser.egg-info/dependency_links.txt
splparser.egg-info/top_level.txt
splparser/lexers/__init__.py
splparser/lexers/abstractlexer.py
splparser/lexers/addinfolexer.py
splparser/lexers/addtotalslexer.py
splparser/lexers/appendcolslexer.py
splparser/lexers/appendlexer.py
splparser/lexers/auditlexer.py
splparser/lexers/bucketlexer.py
splparser/lexers/chartlexer.py
splparser/lexers/collectlexer.py
splparser/lexers/convertlexer.py
splparser/lexers/deduplexer.py
splparser/lexers/deletelexer.py
splparser/lexers/deltalexer.py
splparser/lexers/evallexer.py
splparser/lexers/eventstatslexer.py
splparser/lexers/exportlexer.py
splparser/lexers/extractlexer.py
splparser/lexers/fieldformatlexer.py
splparser/lexers/fieldslexer.py
splparser/lexers/filldownlexer.py
splparser/lexers/fillnulllexer.py
splparser/lexers/gaugelexer.py
splparser/lexers/headlexer.py
splparser/lexers/historylexer.py
splparser/lexers/inputcsvlexer.py
splparser/lexers/inputlookuplexer.py
splparser/lexers/joinlexer.py
splparser/lexers/loadjoblexer.py
splparser/lexers/localoplexer.py
splparser/lexers/lookuplexer.py
splparser/lexers/makemvlexer.py
splparser/lexers/metadatalexer.py
splparser/lexers/multikvlexer.py
splparser/lexers/mvcombinelexer.py
splparser/lexers/mvexpandlexer.py
splparser/lexers/nomvlexer.py
splparser/lexers/outlierlexer.py
splparser/lexers/outputcsvlexer.py
splparser/lexers/outputlookuplexer.py
splparser/lexers/overlaplexer.py
splparser/lexers/rarelexer.py
splparser/lexers/regexlexer.py
splparser/lexers/relevancylexer.py
splparser/lexers/renamelexer.py
splparser/lexers/replacelexer.py
splparser/lexers/reverselexer.py
splparser/lexers/rexlexer.py
splparser/lexers/searchlexer.py
splparser/lexers/sortlexer.py
splparser/lexers/spathlexer.py
splparser/lexers/statslexer.py
splparser/lexers/strcatlexer.py
splparser/lexers/streamstatslexer.py
splparser/lexers/tablelexer.py
splparser/lexers/tagslexer.py
