Metadata-Version: 1.1
Name: splparser
Version: 0.2.0
Summary: A simple parser for the Splunk Processing Language which emits parse trees.
Home-page: http://pypi.python.org/splparser
Author: Sara Alspaugh
Author-email: saraalspaugh@gmail.com
License: BSD
Keywords: Splunk Processing Language SPL parser
Platform: UNKNOWN
Classifier: Development Status :: 4 - Beta
Classifier: Intended Audience :: Developers
Classifier: Intended Audience :: Science/Research
Classifier: Programming Language :: Other
Classifier: Topic :: Software Development :: Compilers
Classifier: License :: OSI Approved :: BSD License
Requires: ply
Requires: nose
